MANIFEST.in
README.md
setup.py
django_nucleus.egg-info/PKG-INFO
django_nucleus.egg-info/SOURCES.txt
django_nucleus.egg-info/dependency_links.txt
django_nucleus.egg-info/requires.txt
django_nucleus.egg-info/top_level.txt
nucleus/__init__.py
nucleus/context_processors.py
nucleus/static/admin/img/icon-addlink.svg
nucleus/static/admin/img/icon-calendar.svg
nucleus/static/admin/img/icon-changelink.svg
nucleus/static/admin/img/icon-clock.svg
nucleus/static/admin/img/icon-deletelink.svg
nucleus/static/admin/img/icon-no.svg
nucleus/static/admin/img/icon-unknown.svg
nucleus/static/admin/img/icon-yes.svg
nucleus/static/admin/img/search.svg
nucleus/static/nucleus/css/app.css
nucleus/static/nucleus/img/chevron-down.svg
nucleus/static/nucleus/img/chevron-right.svg
nucleus/static/nucleus/js/app.js
nucleus/static/nucleus/js/chart.min.js
nucleus/static/nucleus/scss/app.scss
nucleus/static/nucleus/scss/components/_box.scss
nucleus/static/nucleus/scss/components/_chart.scss
nucleus/static/nucleus/scss/components/_heading.scss
nucleus/static/nucleus/scss/components/_label.scss
nucleus/static/nucleus/scss/components/_progress.scss
nucleus/static/nucleus/scss/components/_signed_number.scss
nucleus/static/nucleus/scss/components/_stat_item.scss
nucleus/static/nucleus/scss/helpers/_breadcrumbs.scss
nucleus/static/nucleus/scss/helpers/_buttons.scss
nucleus/static/nucleus/scss/helpers/_changelist.scss
nucleus/static/nucleus/scss/helpers/_commons.scss
nucleus/static/nucleus/scss/helpers/_datepicker.scss
nucleus/static/nucleus/scss/helpers/_elements.scss
nucleus/static/nucleus/scss/helpers/_filter.scss
nucleus/static/nucleus/scss/helpers/_forms.scss
nucleus/static/nucleus/scss/helpers/_grid.scss
nucleus/static/nucleus/scss/helpers/_header.scss
nucleus/static/nucleus/scss/helpers/_history.scss
nucleus/static/nucleus/scss/helpers/_inlines.scss
nucleus/static/nucleus/scss/helpers/_messages.scss
nucleus/static/nucleus/scss/helpers/_module.scss
nucleus/static/nucleus/scss/helpers/_pagination.scss
nucleus/static/nucleus/scss/helpers/_select2.scss
nucleus/static/nucleus/scss/helpers/_selector.scss
nucleus/static/nucleus/scss/helpers/_sidebar.scss
