Metadata-Version: 2.1
Name: django-nucleus
Version: 0.1.2
Summary: Theme for Django admin
Home-page: http://github.com/lukasvinclav/django-nucleus
License: UNKNOWN
Keywords: django admin theme clean minimal ui sidebar
Platform: UNKNOWN
Classifier: Programming Language :: Python
Classifier: Programming Language :: Python :: 3.5
Classifier: Programming Language :: Python :: 3.6
Classifier: Operating System :: OS Independent
Classifier: Environment :: Web Environment
Classifier: Intended Audience :: Developers
Classifier: Framework :: Django
